apps/example_calib.xml
apps/example_data.h5
apps/rotating_source.h5
apps/start_apollo_TA181.sh
apps/start_phantom.sh
apps/start_sounddevice.sh
apps/start_tornado.sh
apps/start_typhoon.sh
apps/FreqBeamformingExample/main.py
apps/FreqBeamformingExample/theme.yaml
apps/FreqBeamformingExample/templates/index.html
apps/FreqBeamformingExample/templates/styles.css
apps/Measurement_App/app.py
apps/Measurement_App/cam.py
apps/Measurement_App/example_data.h5
apps/Measurement_App/layout.py
apps/Measurement_App/log.py
apps/Measurement_App/main.py
apps/Measurement_App/theme.yaml
apps/Measurement_App/threads.py
apps/Measurement_App/acoular_future/__init__.py
apps/Measurement_App/acoular_future/fastFuncs.py
apps/Measurement_App/acoular_future/spectra.py
apps/Measurement_App/acoular_future/tbeamform.py
apps/Measurement_App/acoular_future/tprocess.py
apps/Measurement_App/config_files/settings_apollo.ini
apps/Measurement_App/config_files/settings_typhoon.ini
apps/Measurement_App/metadata/.meta
apps/Measurement_App/micgeom/array_64.xml
apps/Measurement_App/micgeom/minidsp_uma16.xml
apps/Measurement_App/micgeom/transit_vogel_array75_2021.xml
apps/Measurement_App/micgeom/tub_vogel64.xml
apps/Measurement_App/templates/index.html
apps/Measurement_App/templates/styles.css
apps/MicGeomExample/main.py
apps/MicGeomExample/theme.yaml
apps/MicGeomExample/templates/Acoular_logo
apps/MicGeomExample/templates/Acoular_logo_grey.png
apps/MicGeomExample/templates/index.html
apps/MicGeomExample/templates/styles.css
apps/RotatingExample/main.py
apps/RotatingExample/theme.yaml
apps/RotatingExample/templates/index.html
apps/RotatingExample/templates/styles.css
apps/SLM/main.py
apps/SLM/theme.yaml
apps/SLM/templates/index.html
apps/SLM/templates/styles.css
apps/TimeSamplesExample/main.py
apps/TimeSamplesExample/theme.yaml
apps/TimeSamplesExample/templates/index.html
apps/TimeSamplesExample/templates/styles.css
spectacoular/__init__.py
spectacoular/bokehview.py
spectacoular/consumer.py
spectacoular-25.5.post2.dist-info/METADATA
spectacoular-25.5.post2.dist-info/WHEEL
spectacoular-25.5.post2.dist-info/entry_points.txt
spectacoular-25.5.post2.dist-info/licenses/AUTHORS.rst
spectacoular-25.5.post2.dist-info/licenses/LICENSE
spectacoular-25.5.post2.dist-info/RECORD
