Metadata-Version: 2.4
Name: spectacoular
Version: 25.5.post2
Summary: Library for SpectAcoular interactive applications with Acoular
Project-URL: homepage, https://acoular.github.io/spectacoular/
Project-URL: documentation, https://acoular.github.io/spectacoular/
Project-URL: repository, https://github.com/acoular/spectacoular
Author-email: Acoular Development Team <info@acoular.org>
Maintainer-email: Adam Kujawski <adam.kujawski@tu-berlin.de>, Art Pelling <a.pelling@tu-berlin.de>, Ennes Sarradj <ennes.sarradj@tu-berlin.de>, Gert Herold <gert.herold@tu-berlin.de>, Mikolaj Czuchaj <mikolaj.czuchaj@tu-berlin.de>, Simon Jekosch <s.jekosch@tu-berlin.de>
License: BSD 3-Clause License
License-File: AUTHORS.rst
License-File: LICENSE
Keywords: GUI,acoustics,beamforming,microphone array
Classifier: Development Status :: 5 - Production/Stable
Classifier: Intended Audience :: Education
Classifier: Intended Audience :: Science/Research
Classifier: License :: OSI Approved :: BSD License
Classifier: Programming Language :: Python
Classifier: Topic :: Scientific/Engineering :: Physics
Requires-Python: <3.14,>=3.10
Requires-Dist: acoular<=25.04,>=25.01
Requires-Dist: bokeh>=3.0
Provides-Extra: dev
Requires-Dist: graphviz; extra == 'dev'
Requires-Dist: hatch; extra == 'dev'
Requires-Dist: hypothesis; extra == 'dev'
Requires-Dist: ipython; extra == 'dev'
Requires-Dist: matplotlib; extra == 'dev'
Requires-Dist: numpydoc; extra == 'dev'
Requires-Dist: opencv-python; extra == 'dev'
Requires-Dist: pickleshare; extra == 'dev'
Requires-Dist: pytest; extra == 'dev'
Requires-Dist: ruff==0.8.1; extra == 'dev'
Requires-Dist: sounddevice; extra == 'dev'
Requires-Dist: sphinx; extra == 'dev'
Requires-Dist: sphinx-gallery; extra == 'dev'
Provides-Extra: docs
Requires-Dist: graphviz; extra == 'docs'
Requires-Dist: ipython; extra == 'docs'
Requires-Dist: matplotlib; extra == 'docs'
Requires-Dist: numpydoc; extra == 'docs'
Requires-Dist: opencv-python; extra == 'docs'
Requires-Dist: pickleshare; extra == 'docs'
Requires-Dist: sounddevice; extra == 'docs'
Requires-Dist: sphinx; extra == 'docs'
Requires-Dist: sphinx-gallery; extra == 'docs'
Provides-Extra: full
Requires-Dist: opencv-python; extra == 'full'
Requires-Dist: sounddevice; extra == 'full'
Provides-Extra: tapy
Requires-Dist: opencv-python; extra == 'tapy'
Requires-Dist: sounddevice; extra == 'tapy'
Requires-Dist: tapy; extra == 'tapy'
Provides-Extra: tests
Requires-Dist: hypothesis; extra == 'tests'
Requires-Dist: opencv-python; extra == 'tests'
Requires-Dist: pytest; extra == 'tests'
Requires-Dist: sounddevice; extra == 'tests'
